tty_menu.py
tty_menu-1.0.3.dist-info/LICENSE
tty_menu-1.0.3.dist-info/METADATA
tty_menu-1.0.3.dist-info/WHEEL
tty_menu-1.0.3.dist-info/top_level.txt
tty_menu-1.0.3.dist-info/RECORD
