Metadata-Version: 2.1
Name: tty-menu
Version: 1.0.3
Summary: terminal menu(一个命令行上下选择菜单)
Home-page: https://github.com/gojuukaze/tty_menu
Author: gojuukaze
Author-email: i@ikaze.uu.me
License: GUN V3.0
Platform: OSX
Platform: Linux
Classifier: Environment :: Console
Classifier: Intended Audience :: Developers
Classifier: License :: OSI Approved :: GNU General Public License v3 (GPLv3)
Classifier: Operating System :: MacOS
Classifier: Operating System :: POSIX :: Linux
Classifier: Programming Language :: Python :: 2
Classifier: Programming Language :: Python :: 2.6
Classifier: Programming Language :: Python :: 2.7
Classifier: Programming Language :: Python :: 3
Classifier: Programming Language :: Python :: 3.3
Classifier: Programming Language :: Python :: 3.4
Classifier: Programming Language :: Python :: 3.5
Classifier: Programming Language :: Python :: 3.6
Classifier: Programming Language :: Python :: 3.7
Classifier: Development Status :: 5 - Production/Stable
